denova/__init__.py
denova/django_addons/__init__.py
denova/django_addons/apps.py
denova/django_addons/data_image.py
denova/django_addons/models.py
denova/django_addons/run_tests.py
denova/django_addons/settings_shared.py
denova/django_addons/singleton.py
denova/django_addons/utils.py
denova/django_addons/views.py
denova/django_addons/context_processors/__init__.py
denova/django_addons/context_processors/css_selector.py
denova/django_addons/fixtures/sites.site.json
denova/django_addons/middleware/__init__.py
denova/django_addons/middleware/debug.py
denova/django_addons/middleware/proxy404.py
denova/django_addons/middleware/redirect404.py
denova/django_addons/middleware/template.py
denova/django_addons/static/robots.txt
denova/django_addons/static/admin/css/action_icons.css
denova/django_addons/static/admin/css/autocomplete.css
denova/django_addons/static/admin/css/base.css
denova/django_addons/static/admin/css/changelists.css
denova/django_addons/static/admin/css/dashboard.css
denova/django_addons/static/admin/css/fonts.css
denova/django_addons/static/admin/css/forms.css
denova/django_addons/static/admin/css/login.css
denova/django_addons/static/admin/css/object_tools.css
denova/django_addons/static/admin/css/responsive.css
denova/django_addons/static/admin/css/responsive_rtl.css
denova/django_addons/static/admin/css/rtl.css
denova/django_addons/static/admin/css/widgets.css
denova/django_addons/static/admin/css/vendor/select2/LICENSE-SELECT2.md
denova/django_addons/static/admin/css/vendor/select2/select2.css
denova/django_addons/static/admin/css/vendor/select2/select2.min.css
denova/django_addons/static/admin/fonts/LICENSE.txt
denova/django_addons/static/admin/fonts/README.txt
denova/django_addons/static/admin/fonts/Roboto-Bold-webfont.woff
denova/django_addons/static/admin/fonts/Roboto-Light-webfont.woff
denova/django_addons/static/admin/fonts/Roboto-Regular-webfont.woff
denova/django_addons/static/admin/img/LICENSE
denova/django_addons/static/admin/img/README.txt
denova-2.6.5.dist-info/LICENSE
denova-2.6.5.dist-info/METADATA
denova-2.6.5.dist-info/WHEEL
denova-2.6.5.dist-info/top_level.txt
denova-2.6.5.dist-info/RECORD
