Metadata-Version: 2.1
Name: denova
Version: 2.6.5
Summary: Open source python and django enhancements
Home-page: https://denova.com/open/denova_package/
Download-URL: https://github.com/denova-com/denova/
Author: denova.com
Author-email: support@denova.com
Maintainer: denova.com
Maintainer-email: support@denova.com
License: GNU General Public License v3 (GPLv3)
Project-URL: Documentation, https://denova.com/open/denova_package/
Project-URL: Source Code, https://github.com/denova-com/denova/
Keywords: locks logs log-parser openssl
Classifier: Development Status :: 5 - Production/Stable
Classifier: Programming Language :: Python :: 3.5
Classifier: License :: OSI Approved :: GNU General Public License v3 (GPLv3)
Classifier: Operating System :: POSIX :: Linux
Classifier: Intended Audience :: Developers
Classifier: Topic :: Software Development :: Libraries :: Python Modules
Requires-Python: >=3.5
License-File: LICENSE
